emva1288/__init__.py
emva1288/_version.py
emva1288/camera/__init__.py
emva1288/camera/bad_images.py
emva1288/camera/camera.py
emva1288/camera/dataset_generator.py
emva1288/camera/points_generator.py
emva1288/camera/routines.py
emva1288/process/__init__.py
emva1288/process/data.py
emva1288/process/loader.py
emva1288/process/parser.py
emva1288/process/plotting.py
emva1288/process/results.py
emva1288/process/routines.py
emva1288/report/__init__.py
emva1288/report/report.py
emva1288/report/files/EMVA1288Logo.pdf
emva1288/report/files/missinglogo.pdf
emva1288/report/files/missingplot.pdf
emva1288/report/templates/emvadatasheet.sty
emva1288/report/templates/general_info.tex
emva1288/report/templates/op.tex
emva1288/report/templates/op_header.tex
emva1288/report/templates/report.tex
emva1288-1.0.2.dist-info/LICENSE
emva1288-1.0.2.dist-info/METADATA
emva1288-1.0.2.dist-info/WHEEL
emva1288-1.0.2.dist-info/top_level.txt
emva1288-1.0.2.dist-info/RECORD
