Metadata-Version: 2.1
Name: emva1288
Version: 1.0.2
Summary: EMVA1288 reference implementation
Home-page: https://github.com/EMVA1288/emva1288
Author: Federico Ariza
Author-email: ariza.federico@gmail.com
License: GNU Lesser General Public License v3.0
Keywords: sensors,cameras,industrial,standard
Classifier: Programming Language :: Python :: 3
Classifier: Programming Language :: Python :: 3.8
License-File: LICENSE
Requires-Dist: matplotlib
Requires-Dist: numpy
Requires-Dist: pillow
Requires-Dist: lxml
Requires-Dist: scipy
Requires-Dist: jinja2
Provides-Extra: doc
Requires-Dist: sphinx ; extra == 'doc'
Requires-Dist: sphinx-rtd-theme ; extra == 'doc'
Provides-Extra: tests
Requires-Dist: pytest ; extra == 'tests'
Requires-Dist: pytest-flake8 ; extra == 'tests'
